argus/__init__.py
argus/__main__.py
argus/cli/constants.py
argus/cli/helpers.py
argus/cli/logo.py
argus/cli/main.py
argus/cli/status_bar.py
argus/cli/catalog/__init__.py
argus/cli/catalog/loader.py
argus/cli/catalog/model.py
argus/cli/commands/__init__.py
argus/cli/commands/browse.py
argus/cli/commands/favorites.py
argus/cli/commands/flow_control.py
argus/cli/commands/help.py
argus/cli/commands/info.py
argus/cli/commands/run.py
argus/cli/commands/select.py
argus/cli/commands/utility.py
argus/cli/views/__init__.py
argus/cli/views/panels.py
argus/cli/views/table_modules.py
argus/config/__init__.py
argus/config/modules.json
argus/config/settings.py
argus/core/__init__.py
argus/core/cache.py
argus/core/catalog_cache.py
argus/core/http.py
argus/core/runner.py
argus/core/utils.py
argus/modules/__init__.py
argus/modules/api_schema_grabber.py
argus/modules/archive_history.py
argus/modules/asn_lookup.py
argus/modules/associated_hosts.py
argus/modules/attack_surface_delta.py
argus/modules/autocomplete_vulnerability_checker.py
argus/modules/autonomous_neighbor_peering_map.py
argus/modules/bgp_route_analysis.py
argus/modules/breached_credentials_lookup.py
argus/modules/broken_links.py
argus/modules/bug_bounty_program_finder.py
argus/modules/cache_behavior_analyzer.py
argus/modules/captcha_presence_checker.py
argus/modules/carbon_footprint.py
argus/modules/cdn_detection.py
argus/modules/censys.py
argus/modules/certificate_authority_recon.py
argus/modules/clickjacking_test.py
argus/modules/cloud_bucket_exposure.py
argus/modules/cloud_service_enumeration.py
argus/modules/cms_detection.py
argus/modules/content_discovery.py
argus/modules/cookie_scope_diff.py
argus/modules/cookies.py
argus/modules/cors_misconfiguration_scanner.py
argus/modules/crawl_rules.py
argus/modules/crawler.py
argus/modules/csp_deep_analyzer.py
argus/modules/ct_log_query.py
argus/modules/custom_wordlist_generator.py
argus/modules/dark_web_monitoring.py
argus/modules/data_leak.py
argus_recon-2.0.0.dist-info/licenses/LICENSE
argus_recon-2.0.0.dist-info/METADATA
argus_recon-2.0.0.dist-info/WHEEL
argus_recon-2.0.0.dist-info/entry_points.txt
argus_recon-2.0.0.dist-info/top_level.txt
argus_recon-2.0.0.dist-info/RECORD
