Metadata-Version: 2.4
Name: argus-recon
Version: 2.0.0
Summary: Toolkit for information gathering & reconnaissance.
Author-email: Jasonxtn <xtnjason@gmail.com>
License: MIT License
Keywords: recon,security,osint,networking,dns,http,cli
Classifier: Programming Language :: Python :: 3
Classifier: Programming Language :: Python :: 3.10
Classifier: Programming Language :: Python :: 3.11
Classifier: Programming Language :: Python :: 3.12
Classifier: License :: OSI Approved :: MIT License
Classifier: Environment :: Console
Classifier: Topic :: Security
Classifier: Intended Audience :: Information Technology
Classifier: Typing :: Typed
Requires-Python: >=3.10
License-File: LICENSE
Requires-Dist: requests<3,>=2.32
Requires-Dist: urllib3<3,>=2
Requires-Dist: rich<14,>=13
Requires-Dist: dnspython<3,>=2.6
Requires-Dist: paramiko<4,>=3
Requires-Dist: beautifulsoup4<5,>=4.12
Requires-Dist: lxml<6,>=5
Requires-Dist: Jinja2<4,>=3.1
Requires-Dist: packaging<25,>=24
Requires-Dist: python-slugify<9,>=8
Requires-Dist: mmh3<5,>=4
Requires-Dist: idna<4,>=3
Provides-Extra: dev
Requires-Dist: pytest>=8; extra == "dev"
Requires-Dist: ruff>=0.6; extra == "dev"
Requires-Dist: mypy>=1.11; extra == "dev"
Requires-Dist: build>=1.2; extra == "dev"
Requires-Dist: twine>=5; extra == "dev"
Dynamic: license-file
